livekit/__init__.py
livekit/agents/__init__.py
livekit/agents/_exceptions.py
livekit/agents/inference_runner.py
livekit/agents/job.py
livekit/agents/jupyter.py
livekit/agents/log.py
livekit/agents/plugin.py
livekit/agents/py.typed
livekit/agents/types.py
livekit/agents/vad.py
livekit/agents/version.py
livekit/agents/worker.py
livekit/agents/beta/__init__.py
livekit/agents/beta/workflows/__init__.py
livekit/agents/beta/workflows/email_address.py
livekit/agents/cli/__init__.py
livekit/agents/cli/_run.py
livekit/agents/cli/cli.py
livekit/agents/cli/log.py
livekit/agents/cli/proto.py
livekit/agents/cli/watcher.py
livekit/agents/ipc/__init__.py
livekit/agents/ipc/channel.py
livekit/agents/ipc/inference_executor.py
livekit/agents/ipc/inference_proc_executor.py
livekit/agents/ipc/inference_proc_lazy_main.py
livekit/agents/ipc/job_executor.py
livekit/agents/ipc/job_proc_executor.py
livekit/agents/ipc/job_proc_lazy_main.py
livekit/agents/ipc/job_thread_executor.py
livekit/agents/ipc/log_queue.py
livekit/agents/ipc/mock_room.py
livekit/agents/ipc/proc_client.py
livekit/agents/ipc/proc_pool.py
livekit/agents/ipc/proto.py
livekit/agents/ipc/supervised_proc.py
livekit/agents/llm/__init__.py
livekit/agents/llm/_strict.py
livekit/agents/llm/chat_context.py
livekit/agents/llm/fallback_adapter.py
livekit/agents/llm/llm.py
livekit/agents/llm/mcp.py
livekit/agents/llm/realtime.py
livekit/agents/llm/remote_chat_context.py
livekit/agents/llm/tool_context.py
livekit/agents/llm/utils.py
livekit/agents/llm/_provider_format/__init__.py
livekit/agents/llm/_provider_format/anthropic.py
livekit/agents/llm/_provider_format/aws.py
livekit/agents/llm/_provider_format/google.py
livekit/agents/llm/_provider_format/mistralai.py
livekit/agents/llm/_provider_format/openai.py
livekit/agents/llm/_provider_format/utils.py
livekit/agents/metrics/__init__.py
livekit/agents/metrics/base.py
livekit/agents/metrics/usage_collector.py
livekit/agents/metrics/utils.py
livekit/agents/resources/.gitattributes
vyvoj25_framework-1.0.9.dist-info/METADATA
vyvoj25_framework-1.0.9.dist-info/WHEEL
vyvoj25_framework-1.0.9.dist-info/licenses/LICENSE
vyvoj25_framework-1.0.9.dist-info/licenses/NOTICE
vyvoj25_framework-1.0.9.dist-info/RECORD
